kivalu/__init__.py
kivalu-0.25.0.data/scripts/kivalu-setup
kivalu-0.25.0.dist-info/LICENSE
kivalu-0.25.0.dist-info/METADATA
kivalu-0.25.0.dist-info/WHEEL
kivalu-0.25.0.dist-info/top_level.txt
kivalu-0.25.0.dist-info/RECORD
